vector_graphics/__init__.py
vector_graphics/admin_urls.py
vector_graphics/apps.py
vector_graphics/models.py
vector_graphics/permissions.py
vector_graphics/wagtail_hooks.py
vector_graphics/migrations/0001_initial.py
vector_graphics/migrations/__init__.py
vector_graphics/static/vector_graphics/svg/broken_link.svg
vector_graphics/tests/__init__.py
vector_graphics/tests/test_svg_templates.py
vector_graphics-4.1.0.dist-info/AUTHORS.txt
vector_graphics-4.1.0.dist-info/LICENSE.txt
vector_graphics-4.1.0.dist-info/METADATA
vector_graphics-4.1.0.dist-info/WHEEL
vector_graphics-4.1.0.dist-info/top_level.txt
vector_graphics-4.1.0.dist-info/RECORD
